img_processing_hg/__init__.py
img_processing_hg/combination.py
img_processing_hg/io.py
img_processing_hg/plot.py
img_processing_hg/transformation.py
img_processing_hg-0.0.1.dist-info/METADATA
img_processing_hg-0.0.1.dist-info/WHEEL
img_processing_hg-0.0.1.dist-info/top_level.txt
img_processing_hg-0.0.1.dist-info/RECORD
