Metadata-Version: 2.1
Name: img-processing-hg
Version: 0.0.1
Summary: Projeto relativo ao processamento de imagens
Home-page: UNKNOWN
Author: Hugu
License: UNKNOWN
Platform: UNKNOWN
Requires-Python: >=3.9
